enervee_pipeline/__init__.py
enervee_pipeline/config.py
enervee_pipeline/queue_processor.py
enervee_pipeline/storage.py
enervee_pipeline/tests/__init__.py
enervee_pipeline/tests/test_queue_processor.py
enervee_pipeline/tests/test_storage.py
enervee_pipeline/utils/__init__.py
enervee_pipeline/utils/queue.py
enervee_pipeline/utils/string.py
enervee_pipeline-0.0.4.dist-info/METADATA
enervee_pipeline-0.0.4.dist-info/WHEEL
enervee_pipeline-0.0.4.dist-info/top_level.txt
enervee_pipeline-0.0.4.dist-info/RECORD
