Metadata-Version: 2.1
Name: enervee-pipeline
Version: 0.0.4
Summary: Handles sending, receiving and saving data through queues and cloud storage
Home-page: https://gitlab.enervee.com/enervee/enervee_pipeline
Author: David Newcomb
Author-email: david.newcomb@enervee.com
License: MIT
Platform: UNKNOWN
